game/__init__.py
game/game.py
lemon_tictactoe/__init__.py
lemon_tictactoe/exceptions.py
lemon_tictactoe/constants/__init__.py
lemon_tictactoe/constants/exceptions.py
lemon_tictactoe/game/__init__.py
lemon_tictactoe/game/board.py
lemon_tictactoe/game/game.py
lemon_tictactoe/utils/__init__.py
lemon_tictactoe/utils/validator.py
src/__init__.py
src/game/__init__.py
src/game/game.py
utils/__init__.py
utils/validator.py
lemon_tictactoe-0.2.3.dist-info/LICENSE
lemon_tictactoe-0.2.3.dist-info/METADATA
lemon_tictactoe-0.2.3.dist-info/WHEEL
lemon_tictactoe-0.2.3.dist-info/top_level.txt
lemon_tictactoe-0.2.3.dist-info/RECORD
