Metadata-Version: 2.1
Name: lemon-tictactoe
Version: 0.2.3
Summary: A library simplifying the process of embedding a TicTacToe game in your python project.
Home-page: https://github.com/Zitronenjoghurt/Lemon-TicTacToe
Author: Zitronenjoghurt
License: GNU General Public License v3.0
Requires-Python: >=3.9
License-File: LICENSE
Provides-Extra: dev
Requires-Dist: pytest ; extra == 'dev'
Requires-Dist: twine ; extra == 'dev'
Requires-Dist: wheel ; extra == 'dev'
